README.md
setup.py
protein_explorer/__init__.py
protein_explorer.egg-info/PKG-INFO
protein_explorer.egg-info/SOURCES.txt
protein_explorer.egg-info/dependency_links.txt
protein_explorer.egg-info/entry_points.txt
protein_explorer.egg-info/requires.txt
protein_explorer.egg-info/top_level.txt
protein_explorer/analysis/OnTheFly.py
protein_explorer/analysis/__init__.py
protein_explorer/analysis/enhanced_table.py
protein_explorer/analysis/kinase_predictor.py
protein_explorer/analysis/network_kinase_predictor.py
protein_explorer/analysis/networks.py
protein_explorer/analysis/phospho.py
protein_explorer/analysis/phospho_analyzer.py
protein_explorer/analysis/sequence_analyzer.py
protein_explorer/analysis/structure.py
protein_explorer/data/__init__.py
protein_explorer/data/processor.py
protein_explorer/data/scaffold.py
protein_explorer/db/__init__.py
protein_explorer/db/cloud_sql_connector.py
protein_explorer/db/db_integration.py
protein_explorer/navigation/__init__.py
protein_explorer/navigation/network.py
protein_explorer/navigation/paths.py
protein_explorer/utils/__init__.py
protein_explorer/utils/debug_helper.py
protein_explorer/visualization/__init__.py
protein_explorer/visualization/network.py
protein_explorer/visualization/structure.py