Metadata-Version: 2.1
Name: protein-explorer
Version: 0.1.0
Summary: A package for exploring protein structures and phosphorylation sites
Home-page: https://github.com/class-account/protein-explorer
Author: David Vanderwall
Author-email: dvanderwall@hms.harvard.edu
License: UNKNOWN
Platform: UNKNOWN
Classifier: Programming Language :: Python :: 3
Classifier: Programming Language :: Python :: 3.8
Classifier: Programming Language :: Python :: 3.9
Classifier: Programming Language :: Python :: 3.10
Classifier: License :: OSI Approved :: MIT License
Classifier: Operating System :: OS Independent
Classifier: Intended Audience :: Science/Research
Classifier: Topic :: Scientific/Engineering :: Bio-Informatics
Requires-Python: >=3.8
Provides-Extra: database
Provides-Extra: dev
